<templateSet group="user">
  <template name="sys" value="System.out.print(&quot;$END$&quot;);" description="sys" toReformat="false" toShortenFQNames="true">
    <context>
      <option name="JAVA_CODE" value="true" />
      <option name="JAVA_STATEMENT" value="true" />
      <option name="JAVA_EXPRESSION" value="true" />
      <option name="JAVA_DECLARATION" value="true" />
      <option name="JAVA_COMMENT" value="true" />
      <option name="JAVA_STRING" value="true" />
      <option name="COMPLETION" value="true" />
      <option name="JSP" value="true" />
    </context>
  </template>
  <template name="p" value="package " description="package" toReformat="false" toShortenFQNames="true">
    <context>
      <option name="JAVA_CODE" value="true" />
      <option name="JAVA_STATEMENT" value="true" />
      <option name="JAVA_EXPRESSION" value="true" />
      <option name="JAVA_DECLARATION" value="true" />
      <option name="JAVA_COMMENT" value="true" />
      <option name="JAVA_STRING" value="true" />
      <option name="COMPLETION" value="true" />
    </context>
  </template>
  <template name="pc" value="public class " description="public class" toReformat="false" toShortenFQNames="true">
    <context>
      <option name="JAVA_CODE" value="true" />
      <option name="JAVA_STATEMENT" value="true" />
      <option name="JAVA_EXPRESSION" value="true" />
      <option name="JAVA_DECLARATION" value="true" />
      <option name="JAVA_COMMENT" value="true" />
      <option name="JAVA_STRING" value="true" />
      <option name="COMPLETION" value="true" />
    </context>
  </template>
</templateSet>